vibeutils/__init__.py
vibeutils/core.py
vibeutils-0.7.0.dist-info/licenses/LICENSE
vibeutils-0.7.0.dist-info/METADATA
vibeutils-0.7.0.dist-info/WHEEL
vibeutils-0.7.0.dist-info/top_level.txt
vibeutils-0.7.0.dist-info/RECORD
