Metadata-Version: 2.4
Name: vibeutils
Version: 0.7.0
Summary: A Python library that provides various utils using OpenAI and Anthropic APIs
Author-email: Chuyang Deng <chuyangdeng@gmail.com>
License:                                  Apache License
Project-URL: Homepage, https://github.com/pika-orca/vibe-utils
Project-URL: Repository, https://github.com/pika-orca/vibe-utils
Project-URL: Issues, https://github.com/pika-orca/vibe-utils/issues
Keywords: letter counting,text analysis,number comparison,openai,anthropic,nlp
Classifier: Development Status :: 3 - Alpha
Classifier: Intended Audience :: Developers
Classifier: License :: OSI Approved :: MIT License
Classifier: Programming Language :: Python :: 3
Classifier: Programming Language :: Python :: 3.8
Classifier: Programming Language :: Python :: 3.9
Classifier: Programming Language :: Python :: 3.10
Classifier: Programming Language :: Python :: 3.11
Classifier: Programming Language :: Python :: 3.12
Requires-Python: >=3.8
License-File: LICENSE
Requires-Dist: openai>=1.0.0
Provides-Extra: anthropic
Requires-Dist: anthropic>=0.3.0; extra == "anthropic"
Provides-Extra: dev
Requires-Dist: pytest>=7.0; extra == "dev"
Requires-Dist: pytest-cov; extra == "dev"
Requires-Dist: pytest-mock; extra == "dev"
Requires-Dist: black; extra == "dev"
Requires-Dist: flake8; extra == "dev"
Requires-Dist: mypy; extra == "dev"
Requires-Dist: anthropic>=0.3.0; extra == "dev"
Provides-Extra: test
Requires-Dist: pytest>=7.0; extra == "test"
Requires-Dist: pytest-mock; extra == "test"
Requires-Dist: anthropic>=0.3.0; extra == "test"
Dynamic: license-file
Dynamic: requires-python
